YNAB_Weekly-1.0.4-py2.7-nspkg.pth
ynab_weekly/main.py
YNAB_Weekly-1.0.4.dist-info/AUTHORS
YNAB_Weekly-1.0.4.dist-info/LICENSE.md
YNAB_Weekly-1.0.4.dist-info/METADATA
YNAB_Weekly-1.0.4.dist-info/WHEEL
YNAB_Weekly-1.0.4.dist-info/entry_points.txt
YNAB_Weekly-1.0.4.dist-info/namespace_packages.txt
YNAB_Weekly-1.0.4.dist-info/pbr.json
YNAB_Weekly-1.0.4.dist-info/top_level.txt
YNAB_Weekly-1.0.4.dist-info/RECORD
