Metadata-Version: 2.1
Name: YNAB-Weekly
Version: 1.0.4
Summary: Recieve top spending categories in YNAB weekly
Home-page: https://github.com/kotnik/ynab-weekly-spending
Author: Nikola Kotur
Author-email: kotnick@gmail.com
License: Apache-2.0
Platform: UNKNOWN
Classifier: Development Status :: 5 - Production/Stable
Classifier: Environment :: Console
Classifier: Intended Audience :: End Users/Desktop
Classifier: Intended Audience :: Financial and Insurance Industry
Classifier: License :: OSI Approved :: Apache Software License
Classifier: Operating System :: POSIX
Classifier: Topic :: Office/Business :: Financial :: Accounting
Requires-Python: >=2.6, <3
Requires-Dist: certifi (>=14.05.14)
Requires-Dist: six (>=1.10)
Requires-Dist: python-dateutil (>=2.5.3)
Requires-Dist: setuptools (>=21.0.0)
Requires-Dist: urllib3 (>=1.15.1)
Requires-Dist: jinja2 (>=2.10)
Requires-Dist: requests
Requires-Dist: hammock
Requires-Dist: logzero
